SDSParser-0.2.2.dist-info/DESCRIPTION.rst
SDSParser-0.2.2.dist-info/METADATA
SDSParser-0.2.2.dist-info/RECORD
SDSParser-0.2.2.dist-info/WHEEL
SDSParser-0.2.2.dist-info/entry_points.txt
SDSParser-0.2.2.dist-info/metadata.json
SDSParser-0.2.2.dist-info/top_level.txt
sdsparser/__init__.py
sdsparser/__main__.py
sdsparser/configs.py
sdsparser/errors.py
sdsparser/helpers.py
sdsparser/parser.py
sdsparser/regexes.py
sdsparser/update_sds.py
sdsparser/dev/__init__.py
sdsparser/dev/test/__init__.py
sdsparser/dev/test/test_parser.py
sdsparser/development/__init__.py
sdsparser/development/test/__init__.py
sdsparser/development/test/test_parser.py
sdsparser/static/__init__.py
sdsparser/static/regexes.json
static/__init__.py
static/regexes.json
