Metadata-Version: 2.0
Name: SDSParser
Version: 0.2.2
Summary: Extract chemical data from Safety Data Sheet documents
Home-page: https://github.com/astepe/sds_parser
Author: A. Stepe
Author-email: aris@stepe.email
License: LICENSE.txt
Platform: UNKNOWN
Classifier: Programming Language :: Python :: 3
Classifier: License :: OSI Approved :: MIT License
Classifier: Operating System :: OS Independent
Requires-Dist: Pillow (<5.5.0,>=5.4.1)
Requires-Dist: chardet (>=3.0.4,<3.1)
Requires-Dist: pdf2image (>=1.4.0,<1.5)
Requires-Dist: pdfminer.six (==20181108)
Requires-Dist: pycryptodome (>=3.7.3,<3.8.0)
Requires-Dist: pytesseract (>=0.2.6,<0.3.0)
Requires-Dist: six (>=1.12.0,<2.0.0)
Requires-Dist: sortedcontainers (>=2.1.0,<2.2.0)
Requires-Dist: tabulate (>=0.8.3,<0.9.0)
Requires-Dist: tqdm (>=4.31.1,<4.32.0)
